deepl_pro/__init__.py
deepl_pro/py.typed
deepl_pro/translator.py
deepl_pro-0.1.4.dist-info/LICENSE
deepl_pro-0.1.4.dist-info/WHEEL
deepl_pro-0.1.4.dist-info/METADATA
deepl_pro-0.1.4.dist-info/RECORD
